phantom_dev/action_handler/__init__.py
phantom_dev/action_handler/models.py
phantom_dev/app/__init__.py
phantom_dev/app/default_logo.svg
phantom_dev/app/requirements.py
phantom_dev/client/__init__.py
phantom_dev/client/__main__.py
phantom_dev/client/config.py
phantom_dev/client/default_data/connector.py
phantom_dev/client/default_data/readme.html
phantom_dev/client/default_data/requirements-whl.txt
phantom_dev/client/default_data/test_connector.py
phantom_dev/dummy/__init__.py
phantom_dev/dummy/phantom/__init__.py
phantom_dev/dummy/phantom/action_result.py
phantom_dev/dummy/phantom/app.py
phantom_dev/dummy/phantom/base_connector.py
phantom_dev/dummy/phantom/vault.py
phantom_dev-0.14.5.dist-info/LICENSE
phantom_dev-0.14.5.dist-info/METADATA
phantom_dev-0.14.5.dist-info/WHEEL
phantom_dev-0.14.5.dist-info/entry_points.txt
phantom_dev-0.14.5.dist-info/top_level.txt
phantom_dev-0.14.5.dist-info/RECORD
