Metadata-Version: 2.1
Name: phantom-dev
Version: 0.14.5
Summary: Utilities to simplify Phantom app development
Home-page: https://gitlab.com/phantom6/phantom-dev
Author: David Finn
Author-email: dfinn@splunk.com
License: UNKNOWN
Keywords: splunk,phantom
Platform: UNKNOWN
Classifier: License :: OSI Approved :: MIT License
Classifier: Programming Language :: Python :: 3.6
Requires-Python: >=3.6
Requires-Dist: docstring-parser
Requires-Dist: paramiko
Requires-Dist: pytest
Requires-Dist: pyyaml
Requires-Dist: roboversion (>=2)
Requires-Dist: sshtunnel (>=0.4.0)
